{"skeleton":{"hash":"pud/ykCGNROo15BjydCZ5MEpv5k","spine":"3.6.53","width":145,"height":131,"images":"../texiao/"},"bones":[{"name":"root"},{"name":"kzong","parent":"root"},{"name":"k","parent":"kzong"},{"name":"m3/k2_33","parent":"k"},{"name":"theme220_s_8","parent":"root"}],"slots":[{"name":"k","bone":"k","attachment":"theme220_s_8"},{"name":"theme220_s_8","bone":"theme220_s_8"},{"name":"m3/k2_33","bone":"m3/k2_33","attachment":"k2_33","blend":"additive"}],"skins":{"default":{"k":{"theme220_s_8":{"width":105,"height":75}},"m3/k2_33":{"k2_33":{"width":145,"height":131}}}},"animations":{"animation":{"slots":{"m3/k2_33":{"color":[{"time":0,"color":"ffffff00","curve":[0.25,0,0.75,1]},{"time":0.3333,"color":"ffffff33","curve":[0.25,0,0.75,1]},{"time":1,"color":"ffffff00","curve":"stepped"},{"time":1.4333,"color":"ffffff00","curve":[0.25,0,0.75,1]},{"time":2,"color":"ffffff38","curve":[0.25,0,0.75,1]},{"time":2.6667,"color":"ffffff00"}]}},"bones":{"k":{"scale":[{"time":0,"x":1,"y":1,"curve":[0.25,0,0.75,1]},{"time":0.3,"x":1.351,"y":1.351,"curve":[0.25,0,0.75,1]},{"time":0.6667,"x":0.882,"y":0.882,"curve":[0.25,0,0.75,1]},{"time":1.1667,"x":1.078,"y":1.078,"curve":[0.25,0,0.75,1]},{"time":1.5333,"x":0.978,"y":0.978,"curve":[0.25,0,0.75,1]},{"time":1.9,"x":1.147,"y":1.147,"curve":[0.25,0,0.75,1]},{"time":3,"x":1,"y":1}]}}}}}