{"skeleton":{"hash":"vp7Z48CU3+kh/L8Br2iKYJbnlq8","spine":"3.6.53","width":600,"height":100,"images":"../texiao/"},"bones":[{"name":"root"},{"name":"zong","parent":"root"},{"name":"s","parent":"zong"}],"slots":[{"name":"k2","bone":"root"},{"name":"s","bone":"s","attachment":"s_16","blend":"additive"}],"skins":{"default":{"s":{"s_00":{"width":600,"height":100},"s_01":{"width":600,"height":100},"s_02":{"width":600,"height":100},"s_03":{"width":600,"height":100},"s_04":{"width":600,"height":100},"s_05":{"width":600,"height":100},"s_06":{"width":600,"height":100},"s_07":{"width":600,"height":100},"s_08":{"width":600,"height":100},"s_09":{"width":600,"height":100},"s_10":{"width":600,"height":100},"s_11":{"width":600,"height":100},"s_12":{"width":600,"height":100},"s_13":{"width":600,"height":100},"s_14":{"width":600,"height":100},"s_15":{"width":600,"height":100},"s_16":{"width":600,"height":100}}}},"animations":{"animation":{"slots":{"s":{"color":[{"time":0.5333,"color":"ffffffff"},{"time":0.5667,"color":"ffffff00"}],"attachment":[{"time":0,"name":"s_00"},{"time":0.0333,"name":"s_01"},{"time":0.0667,"name":"s_02"},{"time":0.1,"name":"s_03"},{"time":0.1333,"name":"s_04"},{"time":0.1667,"name":"s_05"},{"time":0.2,"name":"s_06"},{"time":0.2333,"name":"s_07"},{"time":0.2667,"name":"s_08"},{"time":0.3,"name":"s_09"},{"time":0.3333,"name":"s_10"},{"time":0.3667,"name":"s_11"},{"time":0.4,"name":"s_12"},{"time":0.4333,"name":"s_13"},{"time":0.4667,"name":"s_14"},{"time":0.5,"name":"s_15"},{"time":0.5333,"name":"s_16"}]}}}}}